{
  "id": "world-002ab-junction-growth",
  "baseCommit": "466246cb5fa70b93960ce5b662224dc479193065",
  "measurementConvention": "rectangular-playable-bounds-square-metres",
  "baseline": {
    "boundsMetres": { "minX": -28, "maxX": 42, "minZ": -28, "maxZ": 28 },
    "widthMetres": 70,
    "depthMetres": 56,
    "playableAreaSquareMetres": 3920,
    "buildingCount": 10,
    "sectorCount": 6
  },
  "milestones": [
    {
      "id": "WORLD-002A",
      "commit": "98b1dd1",
      "boundsMetres": {
        "minX": -36.75,
        "maxX": 50.75,
        "minZ": -28,
        "maxZ": 28
      },
      "widthMetres": 87.5,
      "depthMetres": 56,
      "playableAreaSquareMetres": 4900,
      "growthPercentFromPrior": 25,
      "buildingCount": 16,
      "sectorCount": 10,
      "roadsAddedOrExtended": ["v.road-west-rim", "v.road-east-quay-curve"],
      "sectorsAdded": [
        "sector.west-rim-north",
        "sector.west-rim-south",
        "sector.east-rim-north",
        "sector.east-rim-south"
      ]
    },
    {
      "id": "WORLD-002B",
      "commit": "a53db5d",
      "boundsMetres": {
        "minX": -36.75,
        "maxX": 50.75,
        "minZ": -35,
        "maxZ": 35
      },
      "widthMetres": 87.5,
      "depthMetres": 70,
      "playableAreaSquareMetres": 6125,
      "growthPercentFromPrior": 25,
      "buildingCount": 22,
      "sectorCount": 14,
      "roadsAdded": ["v.road-north-rim", "v.road-south-rim"],
      "sectorsAdded": [
        "sector.north-rim-west",
        "sector.north-rim-east",
        "sector.south-rim-west",
        "sector.south-rim-east"
      ]
    }
  ],
  "finalRelativeToBaseline": {
    "widthGrowthPercent": 25,
    "depthGrowthPercent": 25,
    "areaGrowthPercent": 56.25,
    "westBoundOutwardMetres": 8.75,
    "eastBoundOutwardMetres": 8.75,
    "northBoundOutwardMetres": 7,
    "southBoundOutwardMetres": 7
  },
  "constructionAuthority": "src/world/levels/junctionGrowth.ts",
  "mapAuthority": "testDistrict.definition.mapPresentation",
  "streamingProfile": {
    "selection": "baseline-26-32-24",
    "loadDistanceMetres": 26,
    "unloadDistanceMetres": 32,
    "detailDistanceMetres": 24,
    "reason": "Final-map baseline passed all budgets and sector-center/split ownership removed observed continuity pops; no farther candidate had evidence of additional visible benefit."
  },
  "performance": {
    "referenceViewport": "1280x720",
    "warmupSeconds": 20,
    "measurementSeconds": 60,
    "averageFps": 704.17,
    "onePercentLowFps": 357.14,
    "frameTimeP95Ms": 2.7,
    "drawCalls": 38,
    "triangles": 12891,
    "peakUsedJsHeapProxyMb": 42.1,
    "processWorkingSetAvailable": false,
    "threeCycleOwnershipStable": true,
    "artifact": "docs/screenshots/world-002ab/performance-capture.json",
    "leakArtifact": "docs/screenshots/world-002ab/three-cycle-leak-evidence.json"
  },
  "missionIntegrationEntries": {
    "locationId": "location.ash-001.contact-yard",
    "spawnId": "spawn.ash-001.contact",
    "cameraAnchorId": "camera.ash-001.contact-reveal"
  }
}
